agecrypt/__init__.py
agecrypt/agecrypt.py
agecrypt/assets/icon.icns
agecrypt/assets/icon.png
agecrypt-1.0.0.dist-info/LICENSE
agecrypt-1.0.0.dist-info/METADATA
agecrypt-1.0.0.dist-info/WHEEL
agecrypt-1.0.0.dist-info/entry_points.txt
agecrypt-1.0.0.dist-info/top_level.txt
agecrypt-1.0.0.dist-info/RECORD
