Metadata-Version: 2.1
Name: agecrypt
Version: 1.0.0
Summary: A GUI for age encryption
Home-page: https://github.com/TensorBlast/agecrypt
Author: Ankit Pasi
Author-email: ankitpasi1@gmail.com
Classifier: Programming Language :: Python :: 3
Classifier: License :: OSI Approved :: MIT License
Classifier: Operating System :: OS Independent
Requires-Python: >=3.7
License-File: LICENSE
Requires-Dist: flet>=0.21.0
Requires-Dist: pexpect>=4.8.0
